lsyzwm_master_sdk/__init__.py
lsyzwm_master_sdk/exceptions.py
lsyzwm_master_sdk/rpc_client.py
lsyzwm_master_sdk/zoo_client.py
lsyzwm_master_sdk-0.0.9.dist-info/licenses/LICENSE
lsyzwm_master_sdk-0.0.9.dist-info/METADATA
lsyzwm_master_sdk-0.0.9.dist-info/WHEEL
lsyzwm_master_sdk-0.0.9.dist-info/top_level.txt
lsyzwm_master_sdk-0.0.9.dist-info/RECORD
