Metadata-Version: 2.4
Name: lsyzwm-master-sdk
Version: 0.0.9
Summary: LSYZWM Master SDK - 分布式任务管理系统主节点 SDK，提供 RPC 和 ZooKeeper 客户端
Author: 9kl
License: MIT License
Keywords: lsyzwm,distributed,task,rpc,zookeeper,sdk
Classifier: Development Status :: 3 - Alpha
Classifier: Intended Audience :: Developers
Classifier: Programming Language :: Python :: 3
Classifier: Programming Language :: Python :: 3.8
Classifier: Programming Language :: Python :: 3.9
Classifier: Programming Language :: Python :: 3.10
Classifier: Programming Language :: Python :: 3.11
Classifier: Programming Language :: Python :: 3.12
Requires-Python: >=3.8
License-File: LICENSE
Requires-Dist: kazoo>=2.10.0
Provides-Extra: dev
Provides-Extra: test
Requires-Dist: pytest>=7.0.0; extra == "test"
Requires-Dist: pytest-cov>=4.0.0; extra == "test"
Requires-Dist: pytest-mock>=3.10.0; extra == "test"
Dynamic: license-file
